crs_debuger/__init__.py
crs_debuger/core.py
crs_debuger/exceptions.py
crs_debuger/response.py
tests/__init__.py
tests/test_database.py
tests/test_response.py
crs_debuger-0.4.2.dist-info/LICENSE
crs_debuger-0.4.2.dist-info/METADATA
crs_debuger-0.4.2.dist-info/WHEEL
crs_debuger-0.4.2.dist-info/top_level.txt
crs_debuger-0.4.2.dist-info/RECORD
