Metadata-Version: 2.1
Name: crs-debuger
Version: 0.4.2
Summary: crs debuger
Home-page: https://github.com/ywyt738/crs_debuger
Author: HuangXiaojun
Author-email: huangxiaojun@sightp.com
License: MIT
Platform: UNKNOWN
Classifier: Programming Language :: Python :: 3 :: Only
Classifier: Development Status :: 1 - Planning
Classifier: Operating System :: POSIX :: Linux
Requires-Dist: requests (>=2.20.0)
Requires-Dist: urllib3 (>=1.23)
Requires-Dist: websocket-client (==0.57.0)
Requires-Dist: umsgpack (==0.1.0)
